{
    "version": 1,
    "type": "PLUGIN",
    "name": "Serum",
    "hash": "031e0f253a285531",
    "knobs": [
        {
            "controlIndex": 0,
            "mappedParam": 1,
            "paramHash": "115a743b1e5f",
            "macroParam": true,
            "minValue": 0,
            "maxValue": 16383,
            "controlName": "Macro 1",
            "colorScheme": 21,
            "hapticMode": 0,
            "hapticIndent1": 255,
            "hapticIndent2": 255,
            "hapticSteps": 0,
            "stepNames": [
                "",
                "",
                "",
                "",
                "",
                "",
                "",
                "",
                "",
                "",
                "",
                "",
                "",
                "",
                "",
                ""
            ]
        },
        {
            "controlIndex": 1,
            "mappedParam": 2,
            "paramHash": "351409373902",
            "macroParam": true,
            "minValue": 0,
            "maxValue": 16383,
            "controlName": "Macro 2",
            "colorScheme": 21,
            "hapticMode": 0,
            "hapticIndent1": 255,
            "hapticIndent2": 255,
            "hapticSteps": 0,
            "stepNames": [
                "",
                "",
                "",
                "",
                "",
                "",
                "",
                "",
                "",
                "",
                "",
                "",
                "",
                "",
                "",
                ""
            ]
        },
        {
            "controlIndex": 2,
            "mappedParam": 3,
            "paramHash": "79663a241c7f",
            "macroParam": true,
            "minValue": 0,
            "maxValue": 16383,
            "controlName": "Macro 3",
            "colorScheme": 21,
            "hapticMode": 0,
            "hapticIndent1": 255,
            "hapticIndent2": 255,
            "hapticSteps": 0,
            "stepNames": [
                "",
                "",
                "",
                "",
                "",
                "",
                "",
                "",
                "",
                "",
                "",
                "",
                "",
                "",
                "",
                ""
            ]
        },
        {
            "controlIndex": 3,
            "mappedParam": 4,
            "paramHash": "015c5d476c5d",
            "macroParam": true,
            "minValue": 0,
            "maxValue": 16383,
            "controlName": "Macro 4",
            "colorScheme": 21,
            "hapticMode": 2,
            "hapticIndent1": 255,
            "hapticIndent2": 255,
            "hapticSteps": 0,
            "stepNames": [
                "",
                "",
                "",
                "",
                "",
                "",
                "",
                "",
                "",
                "",
                "",
                "",
                "",
                "",
                "",
                ""
            ]
        },
        {
            "controlIndex": 4,
            "mappedParam": 5,
            "paramHash": "7d3745436d45",
            "macroParam": true,
            "minValue": 0,
            "maxValue": 16383,
            "controlName": "Mod Wheel",
            "colorScheme": 21,
            "hapticMode": 0,
            "hapticIndent1": 255,
            "hapticIndent2": 255,
            "hapticSteps": 0,
            "stepNames": [
                "",
                "",
                "",
                "",
                "",
                "",
                "",
                "",
                "",
                "",
                "",
                "",
                "",
                "",
                "",
                ""
            ]
        },
        {
            "controlIndex": 5,
            "mappedParam": 6,
            "paramHash": "7c2c191b6e41",
            "macroParam": true,
            "minValue": 0,
            "maxValue": 16383,
            "controlName": "Fil Cutoff",
            "colorScheme": 21,
            "hapticMode": 0,
            "hapticIndent1": 255,
            "hapticIndent2": 255,
            "hapticSteps": 0,
            "stepNames": [
                "",
                "",
                "",
                "",
                "",
                "",
                "",
                "",
                "",
                "",
                "",
                "",
                "",
                "",
                "",
                ""
            ]
        },
        {
            "controlIndex": 6,
            "mappedParam": 7,
            "paramHash": "29260b655137",
            "macroParam": true,
            "minValue": 0,
            "maxValue": 16383,
            "controlName": "Fil Driv",
            "colorScheme": 21,
            "hapticMode": 0,
            "hapticIndent1": 255,
            "hapticIndent2": 255,
            "hapticSteps": 0,
            "stepNames": [
                "",
                "",
                "",
                "",
                "",
                "",
                "",
                "",
                "",
                "",
                "",
                "",
                "",
                "",
                "",
                ""
            ]
        },
        {
            "controlIndex": 7,
            "mappedParam": 8,
            "paramHash": "1720564a0329",
            "macroParam": true,
            "minValue": 0,
            "maxValue": 16383,
            "controlName": "Fil Var",
            "colorScheme": 21,
            "hapticMode": 0,
            "hapticIndent1": 255,
            "hapticIndent2": 255,
            "hapticSteps": 0,
            "stepNames": [
                "",
                "",
                "",
                "",
                "",
                "",
                "",
                "",
                "",
                "",
                "",
                "",
                "",
                "",
                "",
                ""
            ]
        }
    ],
    "buttons": []
}